
    {
        "search": {
            "lastGoodList": [
                "notes",
                "note",
                "app",
                "Principality note"
            ],
            "case": false
        },
        "log": {
            "prefix": "INFO",
            "fileName": "enctest.log",
            "active": true
        },
        "file": {
            "postDataUrl": "",
            "datafile": "libtest/TestDataTypes.json",
            "getDataUrl": ""
        },
        "import": {
            "filter": [
                ".csv",
                ".txt",
                ".go",
                ".mod"
            ],
            "path": "/home/stuart/git/golang/enctest/gui/"
        },
        "theme": "dark",
        "data": {
            "assetIsCalled": "Asset",
            "transIsCalled": "Transaction",
            "noteIsCalled": "Note",
            "presentationmode": false,
            "hintIsCalled": "Hint"
        },
        "screen": {
            "width": 1245.833252,
            "height": 547.916626,
            "fullScreen": false,
            "split": 0.223558
        },
        "dialog": {
            "saveTimeOutMS": 3000,
            "copyTimeOutMS": 2500
        }
    }