
    {
        "search": {
            "lastGoodList": [
                "app",
                "note",
                "notes"
            ],
            "case": true
        },
        "getDataUrl": "",
        "screen": {
            "split": 0.2,
            "width": 897.499939,
            "height": 566.25,
            "fullScreen": false
        },
        "data": {
            "noteIsCalled": "Note",
            "presentationmode": true,
            "hintIsCalled": "Hint"
        },
        "log": {
            "active": false,
            "prefix": "INFO",
            "fileName": "enctest.log"
        },
        "datafile": "libtest/TestDataTypes.json",
        "theme": "dark",
        "postDataUrl": "",
        "dialog": {
            "saveTimeOutMS": 3000,
            "copyTimeOutMS": 2500
        }
    }