
    {
        "search": {
            "lastGoodList": [
                "notes",
                "note",
                "app",
                "Principality note"
            ],
            "case": false
        },
        "log": {
            "fileName": "enctest.log",
            "active": true,
            "prefix": "INFO"
        },
        "file": {
            "datafile": "libtest/TestDataTypes.json",
            "getDataUrl": "",
            "postDataUrl": ""
        },
        "import": {
            "csvDateFormat": "02/01/2006",
            "path": "/home/stuart/git/golang/enctest/libtest/",
            "filter": [
                ".csvt",
                ".txt",
                ".go",
                ".mod"
            ],
            "csvSkipHeader": true,
            "csvColumns": [
                "date",
                "type",
                "",
                "",
                "ref",
                "db",
                "cr",
                ""
            ]
        },
        "theme": "dark",
        "data": {
            "presentationmode": false,
            "hintIsCalled": "Hint",
            "assetIsCalled": "Asset",
            "transIsCalled": "Transaction",
            "noteIsCalled": "Note"
        },
        "screen": {
            "split": 0.223558,
            "width": 1038,
            "height": 557,
            "fullScreen": false
        },
        "dialog": {
            "copyTimeOutMS": 2500,
            "saveTimeOutMS": 3000
        }
    }