{
    "groups": {
        "Stuart": {
            "notes": {
                "note": "dHellofg",
                "rt!RT": "# Hi\n\n```go\n\nHippy := 10\n\n```\n\nHow are\n\n## you\n\nToday\n\n"
            },
            "pwHints": {
                "application": {
                    "post": "",
                    "pre": "",
                    "userId": "",
                    "notes": ""
                }
            }
        },
        "UserA": {
            "notes": {
                "note": "An amazing A note (dont panic) fdf",
                "posit": "This is a note"
            },
            "pwHints": {
                "MyApp": {
                    "pre": "abc",
                    "userId": "fakeuser@gmail.com",
                    "notes": "a note to User A",
                    "post": "123"
                },
                "PrincipalityA": {
                    "notes": "https://www.principality.co.uk/en/your-account",
                    "post": "456",
                    "pre": "efg",
                    "userId": "Puser"
                }
            }
        },
        "UserB": {
            "notes": {
                "link": "https://www.principality.co.uk/en/your-account",
                "note for B": "An amazing B note 123"
            },
            "pwHints": {
                "GMail B": {
                    "userId": "another@gmail.com",
                    "notes": "a note to User B",
                    "po!positional": "1234567890",
                    "post": "123 Fred",
                    "pre": "abc",
                    "some More Notes": "hi",
                    "some More!": "hi"
                },
                "Principality B": {
                    "pre": "efg",
                    "userId": "Buser",
                    "link": "https://www.principality.co.uk/en/your-account",
                    "notes": "Principality note",
                    "post": "456"
                }
            }
        }
    },
    "timeStamp": "Fri Jul 30 21:25:10 BST 2021"
}